[
    {
        "id": "appere",
        "tetes": [
            {
                "prenom": "Nathalie",
                "nom": "Appéré"
            }
        ],
        "partis": "PS-PC-G·s-PRG-PP",
        "liste": "Pour Rennes",
        "website": "https://avecnathalieappere.fr/",
        "twitter": "PourRennes",
        "propositions": [
            {
                "id": "appere-p-1",
                "st": "st-21",
                "label": "Créer 5 lignes express de tramways sur roues connectées au métro"
            },
            {
                "id": "appere-p-2",
                "st": "st-13",
                "label": "Baisser fortement les tarifs des abonnements STAR en particulier pour les moins de 25 ans"
            },
            {
                "id": "appere-p-3",
                "st": "st-23",
                "label": "Aménager des places et des rues-jardins dans le centre-ville"
            },
            {
                "id": "appere-p-4",
                "st": "st-12",
                "label": "Ouvrir des maisons de santé dans les quartiers pour garantir l’accès aux soins"
            },
            {
                "id": "appere-p-5",
                "st": "st-19",
                "label": "Créer une police municipale de nuit et une brigade anti-incivilités"
            },
            {
                "id": "appere-p-6",
                "st": "st-7",
                "label": "Transformer le parking Vilaine en un grand espace vert et convivial"
            },
            {
                "id": "appere-p-7",
                "st": "st-22",
                "label": "Faire circuler des navettes électriques dans le centre-ville piétonnier"
            },
            {
                "id": "appere-p-8",
                "st": "st-13",
                "label": "Travailler à un lieu d’accueil permanent pour les femmes victimes de violence"
            },
            {
                "id": "appere-p-9",
                "st": "st-7",
                "label": "Planter 30 000 arbres durant le mandat"
            },
            {
                "id": "appere-p-10",
                "st": "st-20",
                "label": "Déployer un réseau express vélo dans la métropole et des pistes sécurisées dans les communes"
            },
            {
                "id": "appere-p-11",
                "st": "st-2",
                "label": "Créer une Réserve Citoyenne de bénévoles pour les associations"
            }
        ]
    },
    {
        "id": "gandon",
        "tetes": [
            {
                "prenom": "Carole",
                "nom": "Gandon"
            }
        ],
        "parti": "LaREM",
        "liste": "Révéler Rennes",
        "website": "https://reveler-rennes.bzh/",
        "twitter": "RevelerRennes",
        "polemiques": [
            {
                "label": "Mailing malencontreux",
                "references": [
                    {
                        "titre": "",
                        "url": ""
                    }
                ]
            }
        ],
        "propositions": [
            {
                "id": "appere-p-1",
                "st": "st-1",
                "label": "Un truc de fou moi je vous le dis de mieux qu'à gauche !"
            },
            {
                "id": "appere-p-2",
                "st": "st-1",
                "label": "Un truc de fou moi je vous le dis de vraiment mieux qu'à gauche !"
            }
        ]
    },
    {
        "id": "verts",
        "tetes": [
            {
                "prenom": "Matthieu",
                "nom": "Theurier"
            },
            {
                "prenom": "Priscilla",
                "nom": "Zamord"
            }
        ],
        "parti": "EELV-UDB-ND",
        "liste": "Choisir l'écologie pour Rennes",
        "website": "https://rennes-ecologie.bzh/",
        "twitter": "Rennes_Ecologie",
        "propositions": []
    },
    {
        "id": "lepape",
        "tetes": [
            {
                "prenom": "Enora",
                "nom": "Le Pape"
            },
            {
                "prenom": "Jean-Paul",
                "nom": "Tual"
            }
        ],
        "parti": "LFI",
        "liste": "Rennes en commun",
        "website": "https://rennes-en-commun-2020.fr/",
        "twitter": "RennesEnCommun",
        "propositions": []
    },
    {
        "id": "compagnon",
        "tetes": [
            {
                "prenom": "Charles",
                "nom": "Compagnon"
            }
        ],
        "parti": "DVD-LR-MoDem-UDI-PB",
        "liste": "Libres d’agir pour Rennes",
        "website": "https://www.compagnon2020.fr/",
        "twitter": "compagnon2020",
        "propositions": []
    },
    {
        "id": "salmon",
        "tetes": [
            {
                "prenom": "Émeric",
                "nom": "Salmon"
            }
        ],
        "parti": "RN",
        "twitter": "EmericSalmon",
        "propositions": []
    },
    {
        "id": "darcel",
        "tetes": [
            {
                "prenom": "Franck",
                "nom": "Darcel"
            }
        ],
        "parti": "REG",
        "liste": "Rennes Bretagne Europe",
        "website": "http://rbe2020darcel.bzh/",
        "twitter": "RBEdaViken",
        "propositions": []
    },
    {
        "id": "hamon",
        "tetes": [
            {
                "prenom": "Valérie",
                "nom": "Hamon"
            }
        ],
        "parti": "LO",
        "liste": "Lutte ouvrière – faire entendre le camp des travailleurs",
        "website": "https://www.lutte-ouvriere.org/en-regions/bretagne",
        "twitter": "LutteOuvriere",
        "propositions": []
    }
]
